odoo/addons/l10n_th_gov_purchase_guarantee/README.rst
odoo/addons/l10n_th_gov_purchase_guarantee/__init__.py
odoo/addons/l10n_th_gov_purchase_guarantee/__manifest__.py
odoo/addons/l10n_th_gov_purchase_guarantee/data/ir_sequence_data.xml
odoo/addons/l10n_th_gov_purchase_guarantee/data/purchase_guarantee_method_data.xml
odoo/addons/l10n_th_gov_purchase_guarantee/data/purchase_guarantee_type_data.xml
odoo/addons/l10n_th_gov_purchase_guarantee/i18n/l10n_th_gov_purchase_guarantee.pot
odoo/addons/l10n_th_gov_purchase_guarantee/models/__init__.py
odoo/addons/l10n_th_gov_purchase_guarantee/models/account_move.py
odoo/addons/l10n_th_gov_purchase_guarantee/models/purchase_guarantee.py
odoo/addons/l10n_th_gov_purchase_guarantee/models/purchase_guarantee_method.py
odoo/addons/l10n_th_gov_purchase_guarantee/models/purchase_guarantee_type.py
odoo/addons/l10n_th_gov_purchase_guarantee/models/purchase_order.py
odoo/addons/l10n_th_gov_purchase_guarantee/models/purchase_requisition.py
odoo/addons/l10n_th_gov_purchase_guarantee/readme/CONFIGURATION.rst
odoo/addons/l10n_th_gov_purchase_guarantee/readme/CONTRIBUTORS.rst
odoo/addons/l10n_th_gov_purchase_guarantee/readme/DESCRIPTION.rst
odoo/addons/l10n_th_gov_purchase_guarantee/security/ir.model.access.csv
odoo/addons/l10n_th_gov_purchase_guarantee/security/purchase_guarantee_security.xml
odoo/addons/l10n_th_gov_purchase_guarantee/static/description/icon.png
odoo/addons/l10n_th_gov_purchase_guarantee/static/description/index.html
odoo/addons/l10n_th_gov_purchase_guarantee/tests/__init__.py
odoo/addons/l10n_th_gov_purchase_guarantee/tests/test_purchase_guarantee.py
odoo/addons/l10n_th_gov_purchase_guarantee/views/account_move_views.xml
odoo/addons/l10n_th_gov_purchase_guarantee/views/purchase_guarantee_method_views.xml
odoo/addons/l10n_th_gov_purchase_guarantee/views/purchase_guarantee_type_views.xml
odoo/addons/l10n_th_gov_purchase_guarantee/views/purchase_guarantee_views.xml
odoo_addon_l10n_th_gov_purchase_guarantee-15.0.1.1.2.dist-info/METADATA
odoo_addon_l10n_th_gov_purchase_guarantee-15.0.1.1.2.dist-info/WHEEL
odoo_addon_l10n_th_gov_purchase_guarantee-15.0.1.1.2.dist-info/top_level.txt
odoo_addon_l10n_th_gov_purchase_guarantee-15.0.1.1.2.dist-info/RECORD
